{
  "name": "041 - Post-Purchase Upsell",
  "nodes": [
    {
      "parameters": {},
      "id": "node-0",
      "name": "Order Webhook",
      "type": "n8n-nodes-base.webhook",
      "typeVersion": 1,
      "position": [
        250,
        200
      ]
    },
    {
      "parameters": {},
      "id": "node-1",
      "name": "Check Items",
      "type": "n8n-nodes-base.httpRequest",
      "typeVersion": 1,
      "position": [
        450,
        200
      ]
    },
    {
      "parameters": {},
      "id": "node-2",
      "name": "Wait 3 Days",
      "type": "n8n-nodes-base.wait",
      "typeVersion": 1,
      "position": [
        650,
        200
      ]
    },
    {
      "parameters": {},
      "id": "node-3",
      "name": "Send Upsell Email",
      "type": "n8n-nodes-base.slack",
      "typeVersion": 1,
      "position": [
        850,
        200
      ]
    }
  ],
  "connections": {
    "Order Webhook": {
      "main": [
        [
          {
            "node": "Check Items",
            "type": "main",
            "index": 0
          }
        ]
      ]
    },
    "Check Items": {
      "main": [
        [
          {
            "node": "Wait 3 Days",
            "type": "main",
            "index": 0
          }
        ]
      ]
    },
    "Wait 3 Days": {
      "main": [
        [
          {
            "node": "Send Upsell Email",
            "type": "main",
            "index": 0
          }
        ]
      ]
    }
  },
  "active": false,
  "settings": {}
}